periphery/__init__.py
periphery/account/Account.cairo
periphery/account/IAccount.cairo
periphery/account/library.cairo
periphery/introspection/ERC165.cairo
periphery/proxy/Proxy.cairo
periphery/proxy/library.cairo
periphery/test/dapp.cairo
periphery/utils/constants.cairo
ruleslabs_periphery-0.1.1.dev3.dist-info/METADATA
ruleslabs_periphery-0.1.1.dev3.dist-info/WHEEL
ruleslabs_periphery-0.1.1.dev3.dist-info/top_level.txt
ruleslabs_periphery-0.1.1.dev3.dist-info/RECORD
