Metadata-Version: 2.1
Name: ruleslabs-periphery
Version: 0.1.1.dev3
Summary: Periphery smart contracts used by rules.
Home-page: https://github.com/ruleslabs/periphery
Author: 0xChqrles
Author-email: charles@rules.art
License: MIT
Platform: any
Classifier: Operating System :: OS Independent
Requires-Dist: importlib-metadata (>=4.0)
Provides-Extra: testing
Requires-Dist: setuptools ; extra == 'testing'
Requires-Dist: tox ; extra == 'testing'
Requires-Dist: pytest ; extra == 'testing'
